fast_intent_classifier/__init__.py
fast_intent_classifier/classifier.py
fast_intent_classifier/providers/__init__.py
fast_intent_classifier/providers/anthropic.py
fast_intent_classifier/providers/aws_bedrock.py
fast_intent_classifier/providers/azure_openai.py
fast_intent_classifier/providers/base.py
fast_intent_classifier/providers/custom.py
fast_intent_classifier/providers/ollama.py
fast_intent_classifier/providers/openai.py
fast_intent_classifier-0.1.1.dist-info/METADATA
fast_intent_classifier-0.1.1.dist-info/WHEEL
fast_intent_classifier-0.1.1.dist-info/RECORD
