Metadata-Version: 2.3
Name: fast-intent-classifier
Version: 0.1.1
Summary: A fast intent classifier using embeddings
License: MIT
Keywords: intent,classification,embeddings,nlp,machine-learning
Author: Durgesh Rathod
Requires-Python: >=3.8.1,<3.13
Classifier: Development Status :: 4 - Beta
Classifier: Intended Audience :: Developers
Classifier: License :: OSI Approved :: MIT License
Classifier: Programming Language :: Python :: 3
Classifier: Programming Language :: Python :: 3.9
Classifier: Programming Language :: Python :: 3.10
Classifier: Programming Language :: Python :: 3.11
Classifier: Programming Language :: Python :: 3.12
Classifier: Programming Language :: Python :: 3.8
Classifier: Topic :: Scientific/Engineering :: Artificial Intelligence
Classifier: Topic :: Software Development :: Libraries :: Python Modules
Provides-Extra: all
Provides-Extra: anthropic
Provides-Extra: aws
Provides-Extra: openai
Requires-Dist: anthropic (>=0.7.0,<0.8.0) ; extra == "anthropic" or extra == "all"
Requires-Dist: boto3 (>=1.28.0,<2.0.0) ; extra == "aws" or extra == "all"
Requires-Dist: numpy (>=1.24.0,<2.0.0)
Requires-Dist: openai (>=1.0.0,<2.0.0) ; extra == "openai" or extra == "all"
Requires-Dist: pydantic (>=2.0.0,<3.0.0)
Requires-Dist: requests (>=2.31.0,<3.0.0)
Requires-Dist: scikit-learn (>=1.3.0,<2.0.0)
